MANIFEST.in
README.md
setup.py
procemon/__init__.py
procemon/card_back.py
procemon/dex.py
procemon/dex_encoder.py
procemon/monster.py
procemon/monster_type.py
procemon/move.py
procemon/paths.py
procemon/rarity.py
procemon/wv.py
procemon/zine.py
procemon.egg-info/PKG-INFO
procemon.egg-info/SOURCES.txt
procemon.egg-info/dependency_links.txt
procemon.egg-info/requires.txt
procemon.egg-info/top_level.txt
procemon/__pycache__/__init__.cpython-37.pyc
procemon/__pycache__/card_back.cpython-37.pyc
procemon/__pycache__/dex.cpython-37.pyc
procemon/__pycache__/dex_encoder.cpython-37.pyc
procemon/__pycache__/monster.cpython-37.pyc
procemon/__pycache__/monster_type.cpython-37.pyc
procemon/__pycache__/move.cpython-37.pyc
procemon/__pycache__/paths.cpython-37.pyc
procemon/__pycache__/rarity.cpython-37.pyc
procemon/__pycache__/zine.cpython-37.pyc
procemon/data/flavor_text/bad_wikipedia_urls.txt
procemon/data/fonts/Rosette110621-4eVp.ttf
procemon/data/fonts/pokemon-classic.ttf
procemon/data/images/card.png
procemon/data/images/card_back.png
procemon/data/images/logo.png
procemon/data/images/logo_bw.png
procemon/data/images/no_images.txt
procemon/data/images/palette.npy
procemon/data/images/energy/1.png
procemon/data/images/energy/2.png
procemon/data/images/energy/3.png
procemon/data/images/energy/4.png
procemon/data/images/energy/5.png
procemon/data/images/energy/energy.xcf
procemon/data/moves/adjectives.txt
procemon/data/moves/attack_verbs.txt
procemon/data/moves/auxiliary_verbs.txt
procemon/data/moves/moods.txt
procemon/data/moves/src.txt
procemon/data/moves/verbs.txt
procemon/data/regions/japan.txt
procemon/data/regions/us.txt
procemon/data/types/animal.json
procemon/data/types/antenna.json
procemon/data/types/apple.json
procemon/data/types/appliance.json
procemon/data/types/artifact.json
procemon/data/types/balsam.json
procemon/data/types/beverage.json
procemon/data/types/blob.json
procemon/data/types/block.json
procemon/data/types/boat.json
procemon/data/types/book.json
procemon/data/types/bread.json
procemon/data/types/building-material.json
procemon/data/types/cannabis.json
procemon/data/types/carriage.json
