Metadata-Version: 2.1
Name: procemon
Version: 1.5.3
Summary: Procedurally generated trading card game
Home-page: https://github.com/subalterngames/procemon
Author: Seth Alter
Author-email: subalterngames@gmail.com
License: MIT
Keywords: image pokemon card procgen
Platform: UNKNOWN
Classifier: Development Status :: 5 - Production/Stable
Classifier: Intended Audience :: Developers
Classifier: Topic :: Software Development
Classifier: License :: OSI Approved :: MIT License
Classifier: Programming Language :: Python :: 3.6
Classifier: Programming Language :: Python :: 3.7
Classifier: Programming Language :: Python :: 3.8
